README
setup.py
VISIBLE/__init__.py
VISIBLE/matched_filter.py
VISIBLE.egg-info/PKG-INFO
VISIBLE.egg-info/SOURCES.txt
VISIBLE.egg-info/dependency_links.txt
VISIBLE.egg-info/not-zip-safe
VISIBLE.egg-info/requires.txt
VISIBLE.egg-info/top_level.txt