Metadata-Version: 1.1
Name: VISIBLE
Version: 0.1.0
Summary: Matched filtering for interferometric data
Home-page: https://github.com/AstroChem/VISIBLE
Author: Ryan Loomis
Author-email: rloomis@cfa.harvard.edu
License: MIT
Keywords: astronomy science
Platform: UNKNOWN
Classifier: Development Status :: 5 - Production/Stable
Classifier: Environment :: Console
Classifier: Intended Audience :: Science/Research
Classifier: License :: OSI Approved :: MIT License
Classifier: Operating System :: OS Independent
Classifier: Programming Language :: Python :: 2
Classifier: Programming Language :: Python :: 2.7
Classifier: Topic :: Scientific/Engineering :: Astronomy
